lunatask/__init__.py
lunatask/api.py
lunatask/models/__init__.py
lunatask/models/habit.py
lunatask/models/note.py
lunatask/models/people.py
lunatask/models/source.py
lunatask/models/task.py
lunatask/models/timeline_note.py
lunatask_api_python-1.0.0.dist-info/METADATA
lunatask_api_python-1.0.0.dist-info/WHEEL
lunatask_api_python-1.0.0.dist-info/entry_points.txt
lunatask_api_python-1.0.0.dist-info/licenses/LICENSE
lunatask_api_python-1.0.0.dist-info/RECORD
