Metadata-Version: 2.4
Name: lunatask-api-python
Version: 1.0.0
Summary: A Python API for Lunatask
Project-URL: documentation, https://codeberg.org/Taffer/todoist2lunatask/src/branch/main/README.md
Project-URL: homepage, https://codeberg.org/Taffer/todoist2lunatask/
Project-URL: issues, https://codeberg.org/Taffer/todoist2lunatask/issues
Project-URL: source, https://codeberg.org/Taffer/todoist2lunatask/src/branch/main/src/lunatask
Author-email: Chris Herborth <chrish@pobox.com>
Maintainer-email: Chris Herborth <chrish@pobox.com>
License-Expression: CC-BY-NC-ND-4.0
License-File: LICENSE
Keywords: api,import,lunatask,todoist
Classifier: Development Status :: 5 - Production/Stable
Classifier: Environment :: Console
Classifier: Environment :: Web Environment
Classifier: Intended Audience :: Developers
Classifier: Intended Audience :: End Users/Desktop
Classifier: Operating System :: OS Independent
Classifier: Programming Language :: Python :: 3
Classifier: Programming Language :: Python :: 3.11
Classifier: Programming Language :: Python :: 3.12
Classifier: Programming Language :: Python :: 3.13
Classifier: Topic :: Other/Nonlisted Topic
Classifier: Topic :: Software Development :: Libraries :: Python Modules
Requires-Python: >=3.11
Requires-Dist: dataclass-wizard[toml]<1,>=0.35.0
Requires-Dist: requests<3,>=2.32.3
Requires-Dist: todoist-api-python<4,>=3.0
